DocumentFeatureSelection/.DS_Store
DocumentFeatureSelection/__init__.py
DocumentFeatureSelection/init_logger.py
DocumentFeatureSelection/interface.py
DocumentFeatureSelection/models.py
DocumentFeatureSelection/__pycache__/__init__.cpython-34.pyc
DocumentFeatureSelection/__pycache__/__init__.cpython-35.pyc
DocumentFeatureSelection/__pycache__/__init__.cpython-36.pyc
DocumentFeatureSelection/__pycache__/__init__.cpython-37.pyc
DocumentFeatureSelection/__pycache__/init_logger.cpython-34.pyc
DocumentFeatureSelection/__pycache__/init_logger.cpython-35.pyc
DocumentFeatureSelection/__pycache__/init_logger.cpython-36.pyc
DocumentFeatureSelection/__pycache__/init_logger.cpython-37.pyc
DocumentFeatureSelection/__pycache__/interface.cpython-34.pyc
DocumentFeatureSelection/__pycache__/interface.cpython-35.pyc
DocumentFeatureSelection/__pycache__/interface.cpython-36.pyc
DocumentFeatureSelection/__pycache__/models.cpython-34.pyc
DocumentFeatureSelection/__pycache__/models.cpython-35.pyc
DocumentFeatureSelection/__pycache__/models.cpython-36.pyc
DocumentFeatureSelection/__pycache__/models.cpython-37.pyc
DocumentFeatureSelection/bns/__init__.py
DocumentFeatureSelection/bns/bns.py
DocumentFeatureSelection/bns/bns_cython.cpython-35m-darwin.so
DocumentFeatureSelection/bns/bns_cython.cpython-36m-x86_64-linux-gnu.so
DocumentFeatureSelection/bns/bns_cython.cpython-37m-darwin.so
DocumentFeatureSelection/bns/bns_cython.cpython-37m-x86_64-linux-gnu.so
DocumentFeatureSelection/bns/bns_cython.pyx
DocumentFeatureSelection/bns/bns_python3.py
DocumentFeatureSelection/bns/__pycache__/__init__.cpython-34.pyc
DocumentFeatureSelection/bns/__pycache__/__init__.cpython-35.pyc
DocumentFeatureSelection/bns/__pycache__/__init__.cpython-36.pyc
DocumentFeatureSelection/bns/__pycache__/__init__.cpython-37.pyc
DocumentFeatureSelection/bns/__pycache__/bns.cpython-35.pyc
DocumentFeatureSelection/bns/__pycache__/bns.cpython-36.pyc
DocumentFeatureSelection/bns/__pycache__/bns.cpython-37.pyc
DocumentFeatureSelection-1.5.dist-info/LICENSE
DocumentFeatureSelection-1.5.dist-info/METADATA
DocumentFeatureSelection-1.5.dist-info/WHEEL
DocumentFeatureSelection-1.5.dist-info/top_level.txt
DocumentFeatureSelection-1.5.dist-info/RECORD
