Metadata-Version: 2.1
Name: DocumentFeatureSelection
Version: 1.5
Summary: Various methods of feature selection from Text Data
Home-page: https://github.com/Kensuke-Mitsuzawa/DocumentFeatureSelection
Author: kensuke-mi
Author-email: kensuke.mit@gmail.com
License: CeCILL-B
Platform: UNKNOWN
Classifier: Development Status :: 5 - Production/Stable
Classifier: License :: OSI Approved :: MIT License
Classifier: Programming Language :: Python
Classifier: Natural Language :: Japanese
Classifier: Topic :: Scientific/Engineering :: Artificial Intelligence
Classifier: Programming Language :: Python :: 3.5
Requires-Dist: six
Requires-Dist: setuptools (>=1.0)
Requires-Dist: joblib
Requires-Dist: numpy
Requires-Dist: scipy
Requires-Dist: nltk
Requires-Dist: scikit-learn
Requires-Dist: pypandoc
Requires-Dist: cython
Requires-Dist: sqlitedict
Requires-Dist: nose
Requires-Dist: typing
